{
	"invocation": "my test app",
	"intents": [
		{
			"name": "BlueDoorIntent",
			"phrases": [
				"I want to go through the blue door",
				"go through the blue door",
				"through the blue door",
				"the blue door",
				"blue door",
				"blue"
			]
		},
		{
			"name": "RedDoorIntent",
			"phrases": [
				"I want to go through the red door",
				"go through the red door",
				"through the red door",
				"the red door",
				"red door",
				"red"
			]
		},
		{
			"name": "YesIntent",
			"alexa": {
				"name": "AMAZON.YesIntent"
			},
			"phrases": [
				"Yes",
				"yeah",
				"sure",
				"okay",
				"yup",
				"yep",
				"yes please"
			]
		},
		{
			"name": "NoIntent",
			"alexa": {
				"name": "AMAZON.NoIntent"
			},
			"phrases": [
				"No",
				"Nope",
				"nah",
				"negative",
				"no thanks"
			]
		}
	],
	"alexa": {
		"interactionModel": {
			"languageModel": {
				"intents": [
					{
						"name": "AMAZON.CancelIntent",
						"samples": []
					},
					{
						"name": "AMAZON.HelpIntent",
						"samples": []
					},
					{
						"name": "AMAZON.StopIntent",
						"samples": []
					}
				]
			}
		}
	},
	"dialogflow": {
		"intents": [
			{
				"name": "Default Fallback Intent",
				"auto": true,
				"webhookUsed": true,
				"fallbackIntent": true
			},
			{
				"name": "Default Welcome Intent",
				"auto": true,
				"webhookUsed": true,
				"events": [
					{
						"name": "WELCOME"
					}
				]
			}
		]
	}
}
